{
    "version": "https://jsonfeed.org/version/1",
    "title": "Michel Prouff - Peinture",
    "description": "",
    "home_page_url": "https://test.victorprouff.fr",
    "feed_url": "https://test.victorprouff.fr/feed.json",
    "user_comment": "",
    "author": {
        "name": "Michel Prouff"
    },
    "items": [
        {
            "id": "https://test.victorprouff.fr/test.html",
            "url": "https://test.victorprouff.fr/test.html",
            "title": "test",
            "summary": "fzergertshtrhtr",
            "content_html": "<p>fzergertshtrhtr</p>",
            "author": {
                "name": "Michel Prouff"
            },
            "tags": [
            ],
            "date_published": "2021-02-09T18:53:26+01:00",
            "date_modified": "2021-02-09T18:53:26+01:00"
        }
    ]
}
